{
	"archive" : {},
	"artifacts" : 
	[
		{
			"path" : "/home/akashi/project/nanonet/lib/libnanonet.a"
		}
	],
	"backtrace" : 1,
	"backtraceGraph" : 
	{
		"commands" : 
		[
			"add_library"
		],
		"files" : 
		[
			"CMakeLists.txt"
		],
		"nodes" : 
		[
			{
				"file" : 0
			},
			{
				"command" : 0,
				"file" : 0,
				"line" : 9,
				"parent" : 0
			}
		]
	},
	"compileGroups" : 
	[
		{
			"compileCommandFragments" : 
			[
				{
					"fragment" : "-std=gnu++11 -fdiagnostics-color=always"
				}
			],
			"language" : "CXX",
			"languageStandard" : 
			{
				"backtraces" : 
				[
					1
				],
				"standard" : "11"
			},
			"sourceIndexes" : 
			[
				0,
				1,
				2,
				3,
				4,
				5,
				6
			]
		}
	],
	"id" : "nanonet_static::@6890427a1f51a3e7e1df",
	"name" : "nanonet_static",
	"nameOnDisk" : "libnanonet.a",
	"paths" : 
	{
		"build" : ".",
		"source" : "."
	},
	"sourceGroups" : 
	[
		{
			"name" : "Source Files",
			"sourceIndexes" : 
			[
				0,
				1,
				2,
				3,
				4,
				5,
				6
			]
		},
		{
			"name" : "Header Files",
			"sourceIndexes" : 
			[
				7
			]
		}
	],
	"sources" : 
	[
		{
			"backtrace" : 1,
			"compileGroupIndex" : 0,
			"path" : "src/addr.cpp",
			"sourceGroupIndex" : 0
		},
		{
			"backtrace" : 1,
			"compileGroupIndex" : 0,
			"path" : "src/addr_port.cpp",
			"sourceGroupIndex" : 0
		},
		{
			"backtrace" : 1,
			"compileGroupIndex" : 0,
			"path" : "src/port.cpp",
			"sourceGroupIndex" : 0
		},
		{
			"backtrace" : 1,
			"compileGroupIndex" : 0,
			"path" : "src/server_socket.cpp",
			"sourceGroupIndex" : 0
		},
		{
			"backtrace" : 1,
			"compileGroupIndex" : 0,
			"path" : "src/socket.cpp",
			"sourceGroupIndex" : 0
		},
		{
			"backtrace" : 1,
			"compileGroupIndex" : 0,
			"path" : "src/socket_base.cpp",
			"sourceGroupIndex" : 0
		},
		{
			"backtrace" : 1,
			"compileGroupIndex" : 0,
			"path" : "src/udp_socket.cpp",
			"sourceGroupIndex" : 0
		},
		{
			"backtrace" : 1,
			"path" : "src/socket_base.h",
			"sourceGroupIndex" : 1
		}
	],
	"type" : "STATIC_LIBRARY"
}
